lacrm/__init__.py
lacrm/_version.py
lacrm/api.py
lacrm/utils.py
lacrm-1.0.1.dist-info/DESCRIPTION.rst
lacrm-1.0.1.dist-info/METADATA
lacrm-1.0.1.dist-info/RECORD
lacrm-1.0.1.dist-info/WHEEL
lacrm-1.0.1.dist-info/metadata.json
lacrm-1.0.1.dist-info/top_level.txt
