Metadata-Version: 2.0
Name: lacrm
Version: 1.0.1
Summary: lacrm is a basic lessannoyingcrm.com REST API client. The goal is to provide an easy to use interface for the LACRM API.
Home-page: https://github.com/HighMileage/lacrm
Maintainer: Ryan Sellers
Maintainer-email: curiouschiblog@gmail.com
License: MIT
Download-URL: https://github.com/highmileage/lacrm/tarball/1.0.1
Keywords: lacrm less annoying CRM lessannoyingcrm.com
Platform: UNKNOWN
Requires-Dist: requests[security]
